revmap/__init__.py
revmap/encoded.py
revmap/events/__init__.py
revmap/events/keyboard.py
revmap/payloads.py
revmap/revmap.py
revmap/settings/__init__.py
revmap/settings/color_settings.py
revmap/settings/message_settings.py
revmap/settings/variables.py
revmap/utils/__init__.py
revmap/utils/commands.py
revmap/utils/generator_payloads.py
revmap/utils/validator_required.py
revmap-0.0.8.dist-info/LICENSE
revmap-0.0.8.dist-info/METADATA
revmap-0.0.8.dist-info/WHEEL
revmap-0.0.8.dist-info/entry_points.txt
revmap-0.0.8.dist-info/RECORD
