Metadata-Version: 2.1
Name: revmap
Version: 0.0.8
Summary: Ferramenta que gera shell reverso em várias linguagens de programação e codifica
Home-page: https://github.com/joaoviictorti/revmap
License: MIT
Author: João
Author-email: joaovictorti08@gmail.com
Requires-Python: >=3.11,<4.0
Classifier: License :: OSI Approved :: MIT License
Classifier: Programming Language :: Python :: 3
Classifier: Programming Language :: Python :: 3.11
Requires-Dist: prompt-toolkit (==3.0.36)
